{
  "timestamp_utc": "2026-04-14T21:37:42Z",
  "timestamp_jst": "2026-04-15 06:37",
  "version": 3,
  "method": "color_primary",
  "zone": "6h(65-75%)",
  "modes": {
    "F1": 7.66,
    "F2": 13.51,
    "F3": 20.3,
    "F4": 25.29
  },
  "avg24": 7.76,
  "details": {
    "tomsk": {
      "F1": {
        "hz": 7.66,
        "confidence": 1.0,
        "samples": 56,
        "method": "color"
      },
      "F2": {
        "hz": 13.51,
        "confidence": 0.67,
        "samples": 10,
        "method": "color"
      },
      "F3": {
        "hz": 20.3,
        "confidence": 1.0,
        "samples": 58,
        "method": "color"
      },
      "F4": {
        "hz": 25.29,
        "confidence": 1.0,
        "samples": 95,
        "method": "color"
      }
    },
    "cumiana": {
      "source": "Cumiana",
      "status": "unavailable"
    }
  }
}