{
  "timestamp_utc": "2026-04-13T17:45:00Z",
  "timestamp_jst": "2026-04-14 02:45",
  "version": 3,
  "method": "color_primary",
  "zone": "6h(65-75%)",
  "modes": {
    "F1": 7.42,
    "F2": 13.25,
    "F3": 20.58,
    "F4": 25.29
  },
  "avg24": 7.69,
  "details": {
    "tomsk": {
      "F1": {
        "hz": 7.42,
        "confidence": 0.87,
        "samples": 13,
        "method": "color"
      },
      "F2": {
        "hz": 13.25,
        "confidence": 0.13,
        "samples": 2,
        "method": "color"
      },
      "F3": {
        "hz": 20.58,
        "confidence": 1.0,
        "samples": 16,
        "method": "color"
      },
      "F4": {
        "hz": 25.29,
        "confidence": 1.0,
        "samples": 95,
        "method": "color"
      }
    },
    "cumiana": {
      "source": "Cumiana",
      "status": "unavailable"
    }
  }
}