{
  "timestamp": "2026-07-14T05:59:36.046261+00:00",
  "status": "ok",
  "source_line": "https://sos70.ru/provider.php?file=srf.jpg",
  "source_spectro": "https://sos70.ru/provider.php?file=shm.jpg",
  "model": "pixel-extraction-v6.1-ocr",
  "modes": {
    "F1": {
      "hz": 7.89,
      "confidence": 95,
      "calibration": "ocr",
      "amp": 4.85,
      "q": 5.39
    },
    "F2": {
      "hz": 12.98,
      "confidence": 95,
      "calibration": "ocr",
      "amp": 10.97,
      "q": 17.75
    },
    "F3": {
      "hz": 19.62,
      "confidence": 95,
      "calibration": "ocr",
      "amp": 7.7,
      "q": 7.97
    },
    "F4": {
      "hz": 25.23,
      "confidence": 95,
      "calibration": "ocr",
      "amp": 2.04,
      "q": 6.13
    },
    "F5": {
      "hz": null,
      "confidence": 0
    }
  },
  "amplitude_level": "unknown",
  "strongest_mode": "F1",
  "notes": "F1は7.89Hzで基準よりやや高め (+0.06Hz)。軸目盛りOCR検証つきピクセル解析。",
  "polarization": {
    "state": "right",
    "state_jp": "右回転（昼）",
    "japan_hour": 14.98,
    "tomsk_hour": 12.98,
    "is_day_japan": true,
    "is_day_tomsk": true
  },
  "data_age_min": {
    "F1": 30,
    "F2": 65,
    "F3": 70,
    "F4": 30
  }
}