{
  "timestamp": "2026-07-23T23:07:01.045651+00:00",
  "status": "ok",
  "source_line": "https://sos70.ru/provider.php?file=srf.jpg",
  "source_spectro": "https://sos70.ru/provider.php?file=shm.jpg",
  "model": "pixel-extraction-v6.1-ocr",
  "modes": {
    "F1": {
      "hz": 7.93,
      "confidence": 95,
      "calibration": "ocr",
      "amp": 5.92,
      "q": 5.35
    },
    "F2": {
      "hz": 14.23,
      "confidence": 95,
      "calibration": "ocr",
      "amp": 3.12,
      "q": 9.13
    },
    "F3": {
      "hz": 19.99,
      "confidence": 95,
      "calibration": "ocr",
      "amp": 40.03,
      "q": 5.46
    },
    "F4": {
      "hz": 25.71,
      "confidence": 95,
      "calibration": "ocr",
      "amp": 2.98,
      "q": 5.97
    },
    "F5": {
      "hz": null,
      "confidence": 0
    }
  },
  "amplitude_level": "unknown",
  "strongest_mode": "F1",
  "notes": "F1は7.93Hzで基準よりやや高め (+0.10Hz)。軸目盛りOCR検証つきピクセル解析。",
  "polarization": {
    "state": "right",
    "state_jp": "右回転（昼）",
    "japan_hour": 8.12,
    "tomsk_hour": 6.12,
    "is_day_japan": true,
    "is_day_tomsk": true
  },
  "data_age_min": {
    "F1": 22,
    "F2": 37,
    "F3": 32,
    "F4": 27
  }
}