{"code":"ZC","name":"柏崎","lat":37.35,"lon":138.5167,"year":2027,"updated_at":"2026-04-30T08:07:04.678594+00:00","source":"JMA (Japan Meteorological Agency)","days":{"2027-01-01":{"high":[["10:26",19],["21:15",27]],"low":[["04:11",12],["14:07",18]]},"2027-01-02":{"high":[["21:44",29]],"low":[["05:30",10]]},"2027-01-03":{"high":[["22:20",31]],"low":[["06:34",9]]},"2027-01-04":{"high":[["23:03",32]],"low":[["07:24",8]]},"2027-01-05":{"high":[["23:51",33]],"low":[["08:05",8]]},"2027-01-06":{"high":[],"low":[["08:43",7]]},"2027-01-07":{"high":[["00:40",34]],"low":[["09:19",6]]},"2027-01-08":{"high":[["01:26",34],["17:21",24]],"low":[["09:54",4],["19:41",23]]},"2027-01-09":{"high":[["02:10",33],["17:37",22]],"low":[["10:28",3],["20:32",21]]},"2027-01-10":{"high":[["02:50",31],["17:58",21]],"low":[["11:00",2],["21:21",19]]},"2027-01-11":{"high":[["03:29",28],["18:18",20]],"low":[["11:30",1],["22:16",16]]},"2027-01-12":{"high":[["04:07",26],["18:36",19]],"low":[["11:55",2],["23:16",15]]},"2027-01-13":{"high":[["04:48",23],["18:51",19]],"low":[["12:16",4]]},"2027-01-14":{"high":[["05:35",21],["19:03",21]],"low":[["00:21",13],["12:29",7]]},"2027-01-15":{"high":[["06:40",19],["19:19",23]],"low":[["01:28",12],["12:33",11]]},"2027-01-16":{"high":[["08:24",17],["19:44",25]],"low":[["02:37",10],["12:30",15]]},"2027-01-17":{"high":[["20:21",28]],"low":[["03:52",9]]},"2027-01-18":{"high":[["21:15",30]],"low":[["05:07",6]]},"2027-01-19":{"high":[["22:25",32]],"low":[["06:18",4]]},"2027-01-20":{"high":[["23:38",34]],"low":[["07:21",1]]},"2027-01-21":{"high":[],"low":[["08:20",-2]]},"2027-01-22":{"high":[["00:46",35],["16:39",23]],"low":[["09:13",-5],["19:32",21]]},"2027-01-23":{"high":[["01:48",34],["16:56",21]],"low":[["10:02",-6],["20:41",17]]},"2027-01-24":{"high":[["02:47",33],["17:18",19]],"low":[["10:46",-6],["21:52",13]]},"2027-01-25":{"high":[["03:43",30],["17:42",19]],"low":[["11:26",-5],["23:02",10]]},"2027-01-26":{"high":[["04:40",26],["18:08",19]],"low":[["12:03",-2]]},"2027-01-27":{"high":[["05:40",22],["18:33",20]],"low":[["00:06",7],["12:33",3]]},"2027-01-28":{"high":[["06:49",18],["18:58",21]],"low":[["01:09",6],["12:52",8]]},"2027-01-29":{"high":[["08:18",15],["19:21",23]],"low":[["02:16",5],["12:14",12]]},"2027-01-30":{"high":[["19:45",24]],"low":[["03:30",5]]},"2027-01-31":{"high":[["20:15",25]],"low":[["04:55",5]]},"2027-02-01":{"high":[["21:07",26]],"low":[["06:14",5]]},"2027-02-02":{"high":[["22:24",26]],"low":[["07:12",5]]},"2027-02-03":{"high":[["23:36",26]],"low":[["07:57",3]]},"2027-02-04":{"high":[],"low":[["08:34",2]]},"2027-02-05":{"high":[["00:34",26],["16:31",18]],"low":[["09:08",0],["19:07",17]]},"2027-02-06":{"high":[["01:24",25],["16:34",16]],"low":[["09:40",-2],["20:04",14]]},"2027-02-07":{"high":[["02:08",24],["16:46",15]],"low":[["10:08",-3],["20:56",11]]},"2027-02-08":{"high":[["02:49",22],["16:59",14]],"low":[["10:35",-4],["21:45",8]]},"2027-02-09":{"high":[["03:29",20],["17:12",14]],"low":[["11:00",-3],["22:32",6]]},"2027-02-10":{"high":[["04:11",19],["17:23",15]],"low":[["11:21",-1],["23:19",4]]},"2027-02-11":{"high":[["04:57",17],["17:33",16]],"low":[["11:36",2]]},"2027-02-12":{"high":[["05:53",15],["17:48",18]],"low":[["00:08",2],["11:39",6]]},"2027-02-13":{"high":[["07:08",14],["18:10",20]],"low":[["01:02",2],["11:31",9]]},"2027-02-14":{"high":[["18:41",23]],"low":[["02:05",1]]},"2027-02-15":{"high":[["19:26",24]],"low":[["03:22",1]]},"2027-02-16":{"high":[["20:40",25]],"low":[["04:48",0]]},"2027-02-17":{"high":[["22:17",25]],"low":[["06:10",-3]]},"2027-02-18":{"high":[["23:41",26]],"low":[["07:18",-5]]},"2027-02-19":{"high":[["15:44",16]],"low":[["08:14",-8],["18:47",14]]},"2027-02-20":{"high":[["00:51",26],["15:46",14]],"low":[["09:02",-9],["20:00",10]]},"2027-02-21":{"high":[["01:54",25],["16:00",13]],"low":[["09:44",-9],["21:05",5]]},"2027-02-22":{"high":[["02:54",23],["16:19",14]],"low":[["10:22",-8],["22:05",1]]},"2027-02-23":{"high":[["03:52",20],["16:42",14]],"low":[["10:56",-5],["22:59",-2]]},"2027-02-24":{"high":[["04:51",17],["17:04",16]],"low":[["11:25",-1],["23:51",-4]]},"2027-02-25":{"high":[["05:53",14],["17:26",17]],"low":[["11:45",3]]},"2027-02-26":{"high":[["07:01",12],["17:46",18]],"low":[["00:43",-4],["11:31",7]]},"2027-02-27":{"high":[["18:03",19]],"low":[["01:38",-3]]},"2027-02-28":{"high":[["18:21",20]],"low":[["02:41",-1]]},"2027-03-01":{"high":[["18:46",20]],"low":[["04:00",0]]},"2027-03-02":{"high":[["19:43",19]],"low":[["05:33",0]]},"2027-03-03":{"high":[["21:52",18]],"low":[["06:42",0]]},"2027-03-04":{"high":[["23:23",17]],"low":[["07:29",-2]]},"2027-03-05":{"high":[["15:32",12]],"low":[["08:07",-3],["18:48",11]]},"2027-03-06":{"high":[["00:27",17],["15:25",10]],"low":[["08:39",-5],["19:41",7]]},"2027-03-07":{"high":[["01:19",16],["15:30",10]],"low":[["09:07",-6],["20:25",4]]},"2027-03-08":{"high":[["02:06",15],["15:38",9]],"low":[["09:33",-6],["21:06",0]]},"2027-03-09":{"high":[["02:51",14],["15:46",10]],"low":[["09:59",-5],["21:46",-3]]},"2027-03-10":{"high":[["03:38",13],["15:56",11]],"low":[["10:22",-4],["22:26",-5]]},"2027-03-11":{"high":[["04:28",13],["16:09",13]],"low":[["10:42",-1],["23:08",-6]]},"2027-03-12":{"high":[["05:24",12],["16:27",15]],"low":[["10:53",3],["23:54",-7]]},"2027-03-13":{"high":[["06:29",11],["16:51",17]],"low":[["10:46",7]]},"2027-03-14":{"high":[["07:48",11],["17:20",19]],"low":[["00:47",-7],["10:27",9]]},"2027-03-15":{"high":[["17:59",20]],"low":[["01:50",-6]]},"2027-03-16":{"high":[["18:58",19]],"low":[["03:06",-6]]},"2027-03-17":{"high":[["20:38",18]],"low":[["04:34",-6]]},"2027-03-18":{"high":[["22:23",18]],"low":[["05:56",-8]]},"2027-03-19":{"high":[["14:36",10],["23:49",17]],"low":[["07:01",-9],["18:15",8]]},"2027-03-20":{"high":[["14:28",9]],"low":[["07:52",-9],["19:23",4]]},"2027-03-21":{"high":[["01:01",17],["14:37",9]],"low":[["08:35",-9],["20:20",-1]]},"2027-03-22":{"high":[["02:06",16],["14:54",10]],"low":[["09:13",-7],["21:11",-5]]},"2027-03-23":{"high":[["03:09",14],["15:14",12]],"low":[["09:47",-5],["22:00",-8]]},"2027-03-24":{"high":[["04:09",13],["15:37",14]],"low":[["10:16",-1],["22:46",-10]]},"2027-03-25":{"high":[["05:08",12],["15:59",15]],"low":[["10:38",3],["23:30",-10]]},"2027-03-26":{"high":[["06:08",11],["16:20",17]],"low":[["10:36",6]]},"2027-03-27":{"high":[["07:14",10],["16:39",18]],"low":[["00:15",-9],["09:45",9]]},"2027-03-28":{"high":[["16:58",18]],"low":[["01:01",-7]]},"2027-03-29":{"high":[["17:17",17]],"low":[["01:54",-5]]},"2027-03-30":{"high":[["17:40",16]],"low":[["03:00",-4]]},"2027-03-31":{"high":[["18:27",14]],"low":[["04:24",-3]]},"2027-04-01":{"high":[["21:14",11]],"low":[["05:40",-3]]},"2027-04-02":{"high":[["14:19",9],["23:04",10]],"low":[["06:33",-4],["18:32",7]]},"2027-04-03":{"high":[["14:05",8]],"low":[["07:12",-5],["19:09",4]]},"2027-04-04":{"high":[["00:18",10],["14:02",8]],"low":[["07:45",-5],["19:43",0]]},"2027-04-05":{"high":[["01:17",10],["14:05",8]],"low":[["08:14",-4],["20:17",-3]]},"2027-04-06":{"high":[["02:10",10],["14:13",9]],"low":[["08:42",-3],["20:53",-6]]},"2027-04-07":{"high":[["03:03",11],["14:26",11]],"low":[["09:09",-1],["21:30",-9]]},"2027-04-08":{"high":[["03:58",12],["14:45",14]],"low":[["09:34",2],["22:11",-11]]},"2027-04-09":{"high":[["04:54",13],["15:10",16]],"low":[["09:54",5],["22:56",-12]]},"2027-04-10":{"high":[["05:52",13],["15:39",18]],"low":[["09:58",8],["23:45",-12]]},"2027-04-11":{"high":[["06:58",12],["16:14",20]],"low":[["09:46",10]]},"2027-04-12":{"high":[["16:55",20]],"low":[["00:40",-11]]},"2027-04-13":{"high":[["17:48",19]],"low":[["01:43",-10]]},"2027-04-14":{"high":[["19:07",17]],"low":[["02:55",-9]]},"2027-04-15":{"high":[["20:51",15]],"low":[["04:13",-8]]},"2027-04-16":{"high":[["13:09",9],["22:36",13]],"low":[["05:25",-7],["17:28",7]]},"2027-04-17":{"high":[["13:00",9]],"low":[["06:23",-6],["18:35",2]]},"2027-04-18":{"high":[["00:05",12],["13:09",10]],"low":[["07:11",-4],["19:29",-2]]},"2027-04-19":{"high":[["01:21",12],["13:25",12]],"low":[["07:52",-1],["20:18",-6]]},"2027-04-20":{"high":[["02:30",12],["13:46",14]],"low":[["08:27",2],["21:03",-8]]},"2027-04-21":{"high":[["03:32",13],["14:10",17]],"low":[["08:56",5],["21:46",-10]]},"2027-04-22":{"high":[["04:30",13],["14:35",19]],"low":[["09:17",8],["22:27",-10]]},"2027-04-23":{"high":[["05:26",14],["15:00",20]],"low":[["09:14",11],["23:07",-9]]},"2027-04-24":{"high":[["06:22",13],["15:25",21]],"low":[["08:52",12],["23:48",-8]]},"2027-04-25":{"high":[["15:51",21]],"low":[]},"2027-04-26":{"high":[["16:16",20]],"low":[["00:30",-6]]},"2027-04-27":{"high":[["16:44",18]],"low":[["01:17",-5]]},"2027-04-28":{"high":[["17:17",16]],"low":[["02:10",-3]]},"2027-04-29":{"high":[["18:21",13]],"low":[["03:09",-2]]},"2027-04-30":{"high":[["12:52",11],["20:35",10]],"low":[["04:10",-1],["17:32",10]]},"2027-05-01":{"high":[["12:31",11],["22:40",9]],"low":[["05:02",0],["18:12",6]]},"2027-05-02":{"high":[["12:24",11]],"low":[["05:44",1],["18:44",3]]},"2027-05-03":{"high":[["00:11",10],["12:26",13]],"low":[["06:20",3],["19:16",0]]},"2027-05-04":{"high":[["01:21",11],["12:36",15]],"low":[["06:55",5],["19:51",-3]]},"2027-05-05":{"high":[["02:23",13],["12:55",17]],"low":[["07:28",8],["20:29",-5]]},"2027-05-06":{"high":[["03:21",16],["13:21",20]],"low":[["08:00",11],["21:11",-7]]},"2027-05-07":{"high":[["04:17",17],["13:54",23]],"low":[["08:28",13],["21:57",-9]]},"2027-05-08":{"high":[["05:13",18],["14:31",25]],"low":[["08:47",16],["22:46",-10]]},"2027-05-09":{"high":[["06:12",18],["15:14",26]],"low":[["08:57",17],["23:40",-10]]},"2027-05-10":{"high":[["16:02",26]],"low":[]},"2027-05-11":{"high":[["16:57",25]],"low":[["00:36",-9]]},"2027-05-12":{"high":[["18:03",22]],"low":[["01:36",-7]]},"2027-05-13":{"high":[["19:25",19]],"low":[["02:37",-5]]},"2027-05-14":{"high":[["11:14",14],["21:07",16]],"low":[["03:39",-2],["16:07",11]]},"2027-05-15":{"high":[["11:22",15],["22:57",15]],"low":[["04:37",1],["17:27",7]]},"2027-05-16":{"high":[["11:37",17]],"low":[["05:28",5],["18:28",3]]},"2027-05-17":{"high":[["00:32",15],["11:57",19]],"low":[["06:11",8],["19:20",0]]},"2027-05-18":{"high":[["01:56",16],["12:20",22]],"low":[["06:45",12],["20:06",-1]]},"2027-05-19":{"high":[["03:08",18],["12:47",24]],"low":[["07:10",15],["20:48",-2]]},"2027-05-20":{"high":[["04:08",19],["13:16",27]],"low":[["07:20",18],["21:28",-2]]},"2027-05-21":{"high":[["04:59",21],["13:47",28]],"low":[["07:26",20],["22:07",-2]]},"2027-05-22":{"high":[["14:19",29]],"low":[["22:46",-1]]},"2027-05-23":{"high":[["14:53",29]],"low":[["23:26",-1]]},"2027-05-24":{"high":[["15:28",28]],"low":[]},"2027-05-25":{"high":[["16:04",26]],"low":[["00:06",0]]},"2027-05-26":{"high":[["16:43",24]],"low":[["00:47",1]]},"2027-05-27":{"high":[["17:28",21]],"low":[["01:28",2]]},"2027-05-28":{"high":[["10:45",18],["18:32",18]],"low":[["02:06",4],["14:40",17]]},"2027-05-29":{"high":[["10:33",18],["20:13",16]],"low":[["02:40",6],["16:21",14]]},"2027-05-30":{"high":[["10:32",19],["22:25",16]],"low":[["03:12",9],["17:17",11]]},"2027-05-31":{"high":[["10:39",21]],"low":[["03:43",12],["17:59",9]]},"2027-06-01":{"high":[["00:13",17],["10:55",24]],"low":[["04:19",15],["18:38",7]]},"2027-06-02":{"high":[["01:37",20],["11:21",27]],"low":[["05:04",19],["19:20",4]]},"2027-06-03":{"high":[["02:46",23],["11:56",30]],"low":[["05:53",22],["20:06",2]]},"2027-06-04":{"high":[["03:44",26],["12:37",33]],"low":[["06:39",25],["20:55",0]]},"2027-06-05":{"high":[["04:37",27],["13:24",35]],"low":[["07:19",26],["21:47",-2]]},"2027-06-06":{"high":[["05:27",27],["14:15",37]],"low":[["07:54",26],["22:41",-3]]},"2027-06-07":{"high":[["06:16",26],["15:10",37]],"low":[["08:31",26],["23:35",-3]]},"2027-06-08":{"high":[["16:07",35]],"low":[]},"2027-06-09":{"high":[["07:50",23],["17:09",33]],"low":[["00:28",-1],["10:44",22]]},"2027-06-10":{"high":[["08:29",22],["18:17",29]],"low":[["01:20",1],["12:56",20]]},"2027-06-11":{"high":[["09:02",22],["19:41",25]],"low":[["02:10",5],["14:28",17]]},"2027-06-12":{"high":[["09:31",24],["21:29",23]],"low":[["02:57",10],["15:53",15]]},"2027-06-13":{"high":[["09:58",26],["23:29",22]],"low":[["03:39",15],["17:08",12]]},"2027-06-14":{"high":[["10:25",29]],"low":[["04:14",19],["18:12",10]]},"2027-06-15":{"high":[["10:54",32]],"low":[["19:05",9]]},"2027-06-16":{"high":[["11:26",34]],"low":[["19:52",9]]},"2027-06-17":{"high":[["12:01",36]],"low":[["20:33",9]]},"2027-06-18":{"high":[["12:39",38]],"low":[["21:13",9]]},"2027-06-19":{"high":[["13:20",39]],"low":[["21:52",9]]},"2027-06-20":{"high":[["14:01",39]],"low":[["22:30",9]]},"2027-06-21":{"high":[["14:43",38]],"low":[["23:08",9]]},"2027-06-22":{"high":[["15:23",36]],"low":[["23:44",9]]},"2027-06-23":{"high":[["07:08",27],["16:03",34]],"low":[["09:30",26]]},"2027-06-24":{"high":[["07:37",26],["16:44",31]],"low":[["00:18",10],["10:45",25]]},"2027-06-25":{"high":[["08:00",26],["17:31",28]],"low":[["00:47",11],["12:32",24]]},"2027-06-26":{"high":[["08:17",27],["18:33",26]],"low":[["01:10",14],["13:59",22]]},"2027-06-27":{"high":[["08:30",28],["20:10",25]],"low":[["01:26",17],["15:11",21]]},"2027-06-28":{"high":[["08:45",31],["22:27",26]],"low":[["01:36",21],["16:14",19]]},"2027-06-29":{"high":[["09:07",34]],"low":[["01:42",25],["17:10",17]]},"2027-06-30":{"high":[["09:41",37]],"low":[["18:03",15]]},"2027-07-01":{"high":[["10:26",40]],"low":[["18:57",13]]},"2027-07-02":{"high":[["11:19",43]],"low":[["19:51",11]]},"2027-07-03":{"high":[["12:17",45]],"low":[["20:47",9]]},"2027-07-04":{"high":[["13:16",46]],"low":[["21:42",7]]},"2027-07-05":{"high":[["05:12",35],["14:16",46]],"low":[["07:44",34],["22:34",6]]},"2027-07-06":{"high":[["05:41",33],["15:15",45]],"low":[["08:46",31],["23:24",7]]},"2027-07-07":{"high":[["06:11",32],["16:14",43]],"low":[["10:05",28]]},"2027-07-08":{"high":[["06:41",31],["17:18",39]],"low":[["00:11",9],["11:38",26]]},"2027-07-09":{"high":[["07:12",31],["18:30",35]],"low":[["00:54",13],["12:58",23]]},"2027-07-10":{"high":[["07:42",33],["19:59",32]],"low":[["01:34",17],["14:13",21]]},"2027-07-11":{"high":[["08:14",35],["21:55",30]],"low":[["02:07",23],["15:29",20]]},"2027-07-12":{"high":[["08:46",37]],"low":[["02:27",28],["16:45",19]]},"2027-07-13":{"high":[["09:21",40]],"low":[["17:54",19]]},"2027-07-14":{"high":[["10:01",42]],"low":[["18:52",19]]},"2027-07-15":{"high":[["10:47",44]],"low":[["19:40",20]]},"2027-07-16":{"high":[["11:36",45]],"low":[["20:23",19]]},"2027-07-17":{"high":[["12:25",46]],"low":[["21:02",19]]},"2027-07-18":{"high":[["13:13",46]],"low":[["21:40",18]]},"2027-07-19":{"high":[["04:59",36],["13:57",45]],"low":[["07:20",36],["22:15",17]]},"2027-07-20":{"high":[["05:14",35],["14:40",43]],"low":[["08:12",33],["22:47",16]]},"2027-07-21":{"high":[["05:35",34],["15:20",41]],"low":[["09:05",31],["23:17",17]]},"2027-07-22":{"high":[["05:55",33],["16:00",39]],"low":[["10:04",29],["23:43",18]]},"2027-07-23":{"high":[["06:14",33],["16:43",37]],"low":[["11:10",28]]},"2027-07-24":{"high":[["06:28",34],["17:34",35]],"low":[["00:03",20],["12:16",27]]},"2027-07-25":{"high":[["06:40",35],["18:42",33]],"low":[["00:16",24],["13:17",26]]},"2027-07-26":{"high":[["06:56",38],["20:26",33]],"low":[["00:17",27],["14:19",25]]},"2027-07-27":{"high":[["07:19",40]],"low":[["00:09",31],["15:24",25]]},"2027-07-28":{"high":[["07:55",43]],"low":[["16:33",23]]},"2027-07-29":{"high":[["08:47",46]],"low":[["17:41",22]]},"2027-07-30":{"high":[["09:54",48]],"low":[["18:46",19]]},"2027-07-31":{"high":[["11:07",50]],"low":[["19:45",17]]},"2027-08-01":{"high":[["12:16",51]],"low":[["20:41",14]]},"2027-08-02":{"high":[["04:07",39],["13:19",51]],"low":[["06:52",38],["21:33",13]]},"2027-08-03":{"high":[["04:23",38],["14:20",51]],"low":[["07:58",34],["22:20",13]]},"2027-08-04":{"high":[["04:45",37],["15:20",48]],"low":[["09:10",31],["23:03",15]]},"2027-08-05":{"high":[["05:09",36],["16:21",45]],"low":[["10:27",27],["23:43",18]]},"2027-08-06":{"high":[["05:36",37],["17:28",42]],"low":[["11:37",25]]},"2027-08-07":{"high":[["06:03",38],["18:43",38]],"low":[["00:19",23],["12:43",23]]},"2027-08-08":{"high":[["06:32",40],["20:14",36]],"low":[["00:50",28],["13:48",23]]},"2027-08-09":{"high":[["07:02",42]],"low":[["01:04",33],["14:59",23]]},"2027-08-10":{"high":[["07:35",44]],"low":[["16:17",24]]},"2027-08-11":{"high":[["08:18",46]],"low":[["17:35",25]]},"2027-08-12":{"high":[["09:17",46]],"low":[["18:39",25]]},"2027-08-13":{"high":[["10:26",47]],"low":[["19:29",25]]},"2027-08-14":{"high":[["11:29",47]],"low":[["20:11",24]]},"2027-08-15":{"high":[["12:23",47]],"low":[["20:47",23]]},"2027-08-16":{"high":[["03:50",39],["13:11",46]],"low":[["06:49",37],["21:20",22]]},"2027-08-17":{"high":[["03:58",37],["13:55",45]],"low":[["07:40",35],["21:50",21]]},"2027-08-18":{"high":[["04:11",36],["14:37",44]],"low":[["08:30",32],["22:17",21]]},"2027-08-19":{"high":[["04:26",36],["15:18",42]],"low":[["09:20",29],["22:41",22]]},"2027-08-20":{"high":[["04:40",36],["16:01",40]],"low":[["10:10",27],["23:02",24]]},"2027-08-21":{"high":[["04:51",37],["16:49",39]],"low":[["11:00",26],["23:17",27]]},"2027-08-22":{"high":[["05:02",39],["17:48",38]],"low":[["11:50",25],["23:18",31]]},"2027-08-23":{"high":[["05:18",41],["19:06",37]],"low":[["12:43",25],["23:06",34]]},"2027-08-24":{"high":[["05:40",43]],"low":[["13:43",25]]},"2027-08-25":{"high":[["06:12",45]],"low":[["14:54",25]]},"2027-08-26":{"high":[["07:00",47]],"low":[["16:13",24]]},"2027-08-27":{"high":[["08:16",48]],"low":[["17:32",22]]},"2027-08-28":{"high":[["09:50",48]],"low":[["18:40",20]]},"2027-08-29":{"high":[["11:12",49]],"low":[["19:38",18]]},"2027-08-30":{"high":[["03:00",39],["12:22",50]],"low":[["06:07",37],["20:29",17]]},"2027-08-31":{"high":[["03:04",38],["13:26",49]],"low":[["07:14",33],["21:14",17]]},"2027-09-01":{"high":[["03:19",37],["14:27",48]],"low":[["08:19",29],["21:55",18]]},"2027-09-02":{"high":[["03:39",37],["15:29",46]],"low":[["09:25",25],["22:33",21]]},"2027-09-03":{"high":[["04:03",39],["16:33",43]],"low":[["10:26",22],["23:07",25]]},"2027-09-04":{"high":[["04:29",40],["17:41",41]],"low":[["11:24",20],["23:36",30]]},"2027-09-05":{"high":[["04:56",42],["18:53",39]],"low":[["12:20",20],["23:50",34]]},"2027-09-06":{"high":[["05:22",44]],"low":[["13:19",22]]},"2027-09-07":{"high":[["05:49",45]],"low":[["14:24",23]]},"2027-09-08":{"high":[["06:20",45]],"low":[["15:42",25]]},"2027-09-09":{"high":[["07:09",45]],"low":[["17:09",26]]},"2027-09-10":{"high":[["08:37",44]],"low":[["18:16",25]]},"2027-09-11":{"high":[["10:10",44]],"low":[["19:06",25]]},"2027-09-12":{"high":[["02:57",39],["11:24",43]],"low":[["05:41",38],["19:44",23]]},"2027-09-13":{"high":[["02:41",37],["12:21",42]],"low":[["06:30",35],["20:17",23]]},"2027-09-14":{"high":[["02:41",36],["13:09",42]],"low":[["07:14",32],["20:45",22]]},"2027-09-15":{"high":[["02:49",35],["13:54",41]],"low":[["07:56",28],["21:11",22]]},"2027-09-16":{"high":[["02:58",35],["14:39",40]],"low":[["08:37",26],["21:35",23]]},"2027-09-17":{"high":[["03:08",36],["15:24",39]],"low":[["09:18",23],["21:57",25]]},"2027-09-18":{"high":[["03:19",37],["16:14",39]],"low":[["09:59",22],["22:16",28]]},"2027-09-19":{"high":[["03:34",39],["17:09",38]],"low":[["10:42",21],["22:24",31]]},"2027-09-20":{"high":[["03:54",41],["18:12",38]],"low":[["11:29",20],["22:16",34]]},"2027-09-21":{"high":[["04:18",43],["19:28",37]],"low":[["12:22",20],["22:02",36]]},"2027-09-22":{"high":[["04:49",44]],"low":[["13:24",21]]},"2027-09-23":{"high":[["05:29",45]],"low":[["14:37",21]]},"2027-09-24":{"high":[["06:32",44]],"low":[["16:00",20]]},"2027-09-25":{"high":[["08:14",44]],"low":[["17:20",19]]},"2027-09-26":{"high":[["09:57",43]],"low":[["18:25",18]]},"2027-09-27":{"high":[["01:52",36],["11:21",43]],"low":[["05:31",34],["19:18",17]]},"2027-09-28":{"high":[["01:45",35],["12:33",43]],"low":[["06:36",29],["20:03",18]]},"2027-09-29":{"high":[["01:54",35],["13:38",42]],"low":[["07:35",24],["20:43",20]]},"2027-09-30":{"high":[["02:12",36],["14:42",42]],"low":[["08:31",20],["21:20",23]]},"2027-10-01":{"high":[["02:35",38],["15:45",40]],"low":[["09:24",17],["21:53",26]]},"2027-10-02":{"high":[["03:01",40],["16:48",39]],"low":[["10:15",15],["22:21",30]]},"2027-10-03":{"high":[["03:28",42],["17:51",38]],"low":[["11:05",15],["22:34",33]]},"2027-10-04":{"high":[["03:55",43],["19:00",37]],"low":[["11:55",16],["21:41",36]]},"2027-10-05":{"high":[["04:22",43]],"low":[["12:47",18]]},"2027-10-06":{"high":[["04:48",43]],"low":[["13:45",20]]},"2027-10-07":{"high":[["05:16",42]],"low":[["14:55",22]]},"2027-10-08":{"high":[["06:01",40]],"low":[["16:18",22]]},"2027-10-09":{"high":[["07:47",38]],"low":[["17:28",22]]},"2027-10-10":{"high":[["01:57",35],["09:43",36]],"low":[["05:26",34],["18:18",22]]},"2027-10-11":{"high":[["01:31",33],["11:13",35]],"low":[["06:08",31],["18:56",21]]},"2027-10-12":{"high":[["01:24",33],["12:18",35]],"low":[["06:43",27],["19:26",22]]},"2027-10-13":{"high":[["01:25",32],["13:11",35]],"low":[["07:17",24],["19:53",22]]},"2027-10-14":{"high":[["01:30",33],["14:01",35]],"low":[["07:52",21],["20:18",24]]},"2027-10-15":{"high":[["01:40",34],["14:50",35]],"low":[["08:27",18],["20:43",26]]},"2027-10-16":{"high":[["01:54",36],["15:40",36]],"low":[["09:04",16],["21:05",28]]},"2027-10-17":{"high":[["02:15",38],["16:33",37]],"low":[["09:44",15],["21:22",30]]},"2027-10-18":{"high":[["02:40",40],["17:28",37]],"low":[["10:28",14],["21:27",33]]},"2027-10-19":{"high":[["03:10",42],["18:30",36]],"low":[["11:17",14],["21:24",34]]},"2027-10-20":{"high":[["03:44",42]],"low":[["12:12",14]]},"2027-10-21":{"high":[["04:26",42]],"low":[["13:14",14]]},"2027-10-22":{"high":[["05:20",41]],"low":[["14:23",15]]},"2027-10-23":{"high":[["06:39",39]],"low":[["15:39",15]]},"2027-10-24":{"high":[["08:21",37]],"low":[["16:51",16]]},"2027-10-25":{"high":[["00:31",31],["10:05",36]],"low":[["04:42",29],["17:51",17]]},"2027-10-26":{"high":[["00:22",31],["11:36",35]],"low":[["05:52",24],["18:41",19]]},"2027-10-27":{"high":[["00:31",32],["12:53",35]],"low":[["06:49",20],["19:23",21]]},"2027-10-28":{"high":[["00:49",34],["14:02",35]],"low":[["07:41",16],["20:01",24]]},"2027-10-29":{"high":[["01:12",36],["15:07",36]],"low":[["08:30",13],["20:34",27]]},"2027-10-30":{"high":[["01:39",38],["16:07",36]],"low":[["09:17",11],["21:00",30]]},"2027-10-31":{"high":[["02:09",40],["17:04",36]],"low":[["10:02",11],["21:10",32]]},"2027-11-01":{"high":[["02:40",41],["18:00",35]],"low":[["10:47",11],["20:55",34]]},"2027-11-02":{"high":[["03:11",42]],"low":[["11:31",13]]},"2027-11-03":{"high":[["03:42",41]],"low":[["12:17",14]]},"2027-11-04":{"high":[["04:14",40]],"low":[["13:07",15]]},"2027-11-05":{"high":[["04:49",37]],"low":[["14:01",17]]},"2027-11-06":{"high":[["05:33",34]],"low":[["15:01",17]]},"2027-11-07":{"high":[["06:51",31]],"low":[["16:00",18]]},"2027-11-08":{"high":[["00:12",29],["08:50",28],["23:58",29]],"low":[["05:07",27],["16:51",19]]},"2027-11-09":{"high":[["10:53",27],["23:55",29]],"low":[["05:52",24],["17:31",21]]},"2027-11-10":{"high":[["12:18",28],["23:59",31]],"low":[["06:27",20],["18:05",22]]},"2027-11-11":{"high":[["13:22",29]],"low":[["06:59",17],["18:35",24]]},"2027-11-12":{"high":[["00:10",32],["14:18",31]],"low":[["07:33",15],["19:06",26]]},"2027-11-13":{"high":[["00:29",35],["15:10",32]],"low":[["08:09",13],["19:35",29]]},"2027-11-14":{"high":[["00:56",37],["16:00",34]],"low":[["08:49",11],["20:03",30]]},"2027-11-15":{"high":[["01:29",39],["16:50",34]],"low":[["09:33",9],["20:25",32]]},"2027-11-16":{"high":[["02:07",41],["17:43",34]],"low":[["10:21",8],["20:41",32]]},"2027-11-17":{"high":[["02:49",41],["18:41",32]],"low":[["11:13",7],["20:53",32]]},"2027-11-18":{"high":[["03:36",41]],"low":[["12:07",7]]},"2027-11-19":{"high":[["04:30",40]],"low":[["13:04",8]]},"2027-11-20":{"high":[["05:32",37]],"low":[["14:03",9]]},"2027-11-21":{"high":[["06:48",33],["22:27",27]],"low":[["15:03",11]]},"2027-11-22":{"high":[["08:25",30],["22:41",27]],"low":[["03:13",24],["16:02",14]]},"2027-11-23":{"high":[["10:19",28],["23:00",29]],"low":[["04:42",20],["16:56",18]]},"2027-11-24":{"high":[["12:03",28],["23:23",31]],"low":[["05:51",16],["17:43",22]]},"2027-11-25":{"high":[["13:33",29],["23:51",34]],"low":[["06:49",13],["18:24",25]]},"2027-11-26":{"high":[["14:50",31]],"low":[["07:39",10],["18:58",28]]},"2027-11-27":{"high":[["00:22",37],["15:51",32]],"low":[["08:26",9],["19:21",30]]},"2027-11-28":{"high":[["00:56",39],["16:41",33]],"low":[["09:09",8],["19:35",32]]},"2027-11-29":{"high":[["01:33",40],["17:24",33]],"low":[["09:52",8],["19:50",32]]},"2027-11-30":{"high":[["02:10",40]],"low":[["10:33",9]]},"2027-12-01":{"high":[["02:48",39]],"low":[["11:13",9]]},"2027-12-02":{"high":[["03:26",38]],"low":[["11:54",9]]},"2027-12-03":{"high":[["04:03",35]],"low":[["12:33",10]]},"2027-12-04":{"high":[["04:41",32]],"low":[["13:10",11]]},"2027-12-05":{"high":[["05:23",29],["21:40",25]],"low":[["13:44",12]]},"2027-12-06":{"high":[["06:18",25],["21:50",25]],"low":[["02:09",24],["14:12",15]]},"2027-12-07":{"high":[["07:49",23],["21:57",26]],"low":[["03:57",21],["14:32",17]]},"2027-12-08":{"high":[["10:23",22],["22:08",28]],"low":[["05:04",18],["14:47",20]]},"2027-12-09":{"high":[["22:26",30]],"low":[["05:50",16]]},"2027-12-10":{"high":[["22:55",33]],"low":[["06:30",13]]},"2027-12-11":{"high":[["23:32",35]],"low":[["07:10",11]]},"2027-12-12":{"high":[],"low":[["07:53",8]]},"2027-12-13":{"high":[["00:15",37],["16:29",31]],"low":[["08:39",6],["19:01",30]]},"2027-12-14":{"high":[["01:04",39],["17:08",31]],"low":[["09:28",4],["19:42",30]]},"2027-12-15":{"high":[["01:55",40],["17:48",29]],"low":[["10:19",2],["20:22",28]]},"2027-12-16":{"high":[["02:48",40],["18:27",27]],"low":[["11:09",0],["21:09",26]]},"2027-12-17":{"high":[["03:43",38],["19:05",25]],"low":[["11:59",1],["22:13",24]]},"2027-12-18":{"high":[["04:40",36],["19:40",24]],"low":[["12:48",2],["23:56",21]]},"2027-12-19":{"high":[["05:42",32],["20:12",23]],"low":[["13:34",5]]},"2027-12-20":{"high":[["06:56",27],["20:43",24]],"low":[["01:35",18],["14:18",10]]},"2027-12-21":{"high":[["08:35",24],["21:14",26]],"low":[["03:03",15],["14:58",15]]},"2027-12-22":{"high":[["10:44",22],["21:46",29]],"low":[["04:27",13],["15:30",19]]},"2027-12-23":{"high":[["22:22",31]],"low":[["05:42",10]]},"2027-12-24":{"high":[["23:02",34]],"low":[["06:45",9]]},"2027-12-25":{"high":[["23:45",35]],"low":[["07:38",8]]},"2027-12-26":{"high":[],"low":[["08:25",7]]},"2027-12-27":{"high":[["00:30",36]],"low":[["09:07",6]]},"2027-12-28":{"high":[["01:15",37]],"low":[["09:46",6]]},"2027-12-29":{"high":[["01:59",36],["17:45",27]],"low":[["10:24",5],["20:09",26]]},"2027-12-30":{"high":[["02:41",35],["18:08",25]],"low":[["10:59",4],["20:55",23]]},"2027-12-31":{"high":[["03:21",32],["18:30",23]],"low":[["11:31",4],["21:48",21]]}}}